drizzle/__init__.py
drizzle/cdrizzle.cpython-314t-x86_64-linux-gnu.so
drizzle/resample.py
drizzle/util.py
drizzle/utils.py
drizzle/tests/__init__.py
drizzle/tests/helpers.py
drizzle/tests/test_cdrizzle.py
drizzle/tests/test_overlap_calc.py
drizzle/tests/test_resample.py
drizzle/tests/test_utils.py
drizzle-2.2.0.dist-info/METADATA
drizzle-2.2.0.dist-info/WHEEL
drizzle-2.2.0.dist-info/top_level.txt
drizzle-2.2.0.dist-info/RECORD
drizzle-2.2.0.dist-info/licenses/LICENSE.rst
