Metadata-Version: 2.4
Name: drizzle
Version: 2.2.0
Summary: A package for combining dithered images into a single image
Author: STScI
Project-URL: Homepage, https://github.com/spacetelescope/drizzle
Project-URL: Bug Tracker, https://github.com/spacetelescope/drizzle/issues
Project-URL: Documentation, http://spacetelescope.github.io/drizzle/
Project-URL: Source Code, https://github.com/spacetelescope/drizzle
Requires-Python: >=3.10
License-File: LICENSE.rst
Requires-Dist: numpy
Provides-Extra: test
Requires-Dist: astropy; extra == "test"
Requires-Dist: gwcs; extra == "test"
Requires-Dist: pytest>=9.0; extra == "test"
Requires-Dist: pytest-cov; extra == "test"
Requires-Dist: pytest-doctestplus; extra == "test"
Provides-Extra: docs
Requires-Dist: tomli; python_version < "3.11" and extra == "docs"
Requires-Dist: sphinx; extra == "docs"
Requires-Dist: sphinx-automodapi; extra == "docs"
Requires-Dist: sphinx-rtd-theme; extra == "docs"
Requires-Dist: matplotlib; extra == "docs"
Requires-Dist: pytest-doctestplus; extra == "docs"
Dynamic: license-file
